Metadata-Version: 1.0
Name: matrix-factorization-Funsvd
Version: 0.1
Summary: Maxtrix factorization for recommendation
Home-page: UNKNOWN
Author: Mbogol Touye
Author-email: touyejunior@gmail.com
License: UNKNOWN
Platform: UNKNOWN
